<?xml version="1.0" encoding="UTF-8"?>
<current><city id="0" name="Weatogue"><coord lon="-72.8253" lat="41.8372"></coord><country>US</country><timezone>-14400</timezone><sun rise="2022-06-25T09:17:28" set="2022-06-26T00:30:16"></sun></city><temperature value="64.99" min="60.91" max="68.5" unit="fahrenheit"></temperature><feels_like value="65.57" unit="fahrenheit"></feels_like><humidity value="93" unit="%"></humidity><pressure value="1008" unit="hPa"></pressure><wind><speed value="2.62" unit="mph" name="Calm"></speed><gusts value="2.51"></gusts><direction value="281" code="W" name="West"></direction></wind><clouds value="18" name="few clouds"></clouds><visibility value="10000"></visibility><precipitation mode="no"></precipitation><weather number="801" value="few clouds" icon="02n"></weather><lastupdate value="2022-06-25T05:52:09"></lastupdate></current>