<?xml version="1.0" encoding="UTF-8"?>
<current><city id="0" name="Dunedin"><coord lon="-82.7794" lat="28.0284"></coord><country>US</country><timezone>-14400</timezone><sun rise="2022-04-03T11:18:55" set="2022-04-03T23:49:28"></sun></city><temperature value="66.63" min="64.02" max="69.75" unit="fahrenheit"></temperature><feels_like value="66.94" unit="fahrenheit"></feels_like><humidity value="84" unit="%"></humidity><pressure value="1012" unit="hPa"></pressure><wind><speed value="5.01" unit="mph" name="Light breeze"></speed><gusts value="13"></gusts><direction value="321" code="NW" name="Northwest"></direction></wind><clouds value="100" name="overcast clouds"></clouds><visibility value="10000"></visibility><precipitation mode="no"></precipitation><weather number="804" value="overcast clouds" icon="04n"></weather><lastupdate value="2022-04-03T08:49:22"></lastupdate></current>