<?xml version="1.0" encoding="UTF-8"?>
<current><city id="0" name="West New York"><coord lon="-74.0115" lat="40.7888"></coord><country>US</country><timezone>-14400</timezone><sun rise="2021-08-08T09:59:35" set="2021-08-09T00:03:48"></sun></city><temperature value="68.81" min="65.19" max="74.59" unit="fahrenheit"></temperature><feels_like value="69.48" unit="fahrenheit"></feels_like><humidity value="87" unit="%"></humidity><pressure value="1020" unit="hPa"></pressure><wind><speed value="11.5" unit="mph" name="Gentle Breeze"></speed><gusts value="17.27"></gusts><direction value="60" code="ENE" name="East-northeast"></direction></wind><clouds value="90" name="overcast clouds"></clouds><visibility value="9656"></visibility><precipitation mode="no"></precipitation><weather number="701" value="mist" icon="50n"></weather><lastupdate value="2021-08-09T00:24:18"></lastupdate></current>