<?xml version="1.0" encoding="UTF-8"?>
<current><city id="0" name="Weatogue"><coord lon="-72.8253" lat="41.8372"></coord><country>US</country><timezone>-18000</timezone><sun rise="2021-12-21T12:15:37" set="2021-12-21T21:23:24"></sun></city><temperature value="34.88" min="30.97" max="37.67" unit="fahrenheit"></temperature><feels_like value="34.88" unit="fahrenheit"></feels_like><humidity value="73" unit="%"></humidity><pressure value="1011" unit="hPa"></pressure><wind><speed value="1.01" unit="mph" name="Calm"></speed><gusts value="1.99"></gusts><direction value="330" code="NNW" name="North-northwest"></direction></wind><clouds value="75" name="broken clouds"></clouds><visibility value="10000"></visibility><precipitation mode="no"></precipitation><weather number="803" value="broken clouds" icon="04n"></weather><lastupdate value="2021-12-21T22:04:47"></lastupdate></current>