<?xml version="1.0" encoding="UTF-8"?>
<current><city id="0" name="Weatogue"><coord lon="-72.8253" lat="41.8372"></coord><country>US</country><timezone>-14400</timezone><sun rise="2022-05-13T09:33:22" set="2022-05-14T00:02:03"></sun></city><temperature value="63.19" min="61.41" max="65.14" unit="fahrenheit"></temperature><feels_like value="63.73" unit="fahrenheit"></feels_like><humidity value="96" unit="%"></humidity><pressure value="1026" unit="hPa"></pressure><wind><speed value="0" unit="mph" name="Setting"></speed><gusts></gusts><direction></direction></wind><clouds value="100" name="overcast clouds"></clouds><visibility value="10000"></visibility><precipitation mode="no"></precipitation><weather number="701" value="mist" icon="50d"></weather><lastupdate value="2022-05-13T11:41:10"></lastupdate></current>