<?xml version="1.0" encoding="UTF-8"?>
<current><city id="0" name="West New York"><coord lon="-74.0115" lat="40.7888"></coord><country>US</country><timezone>-14400</timezone><sun rise="2022-04-02T10:37:44" set="2022-04-02T23:21:07"></sun></city><temperature value="50.14" min="47.43" max="53.82" unit="fahrenheit"></temperature><feels_like value="46.54" unit="fahrenheit"></feels_like><humidity value="36" unit="%"></humidity><pressure value="1017" unit="hPa"></pressure><wind><speed value="12.66" unit="mph" name="Moderate breeze"></speed><gusts value="17.27"></gusts><direction value="300" code="WNW" name="West-northwest"></direction></wind><clouds value="0" name="clear sky"></clouds><visibility value="10000"></visibility><precipitation mode="no"></precipitation><weather number="800" value="clear sky" icon="01d"></weather><lastupdate value="2022-04-02T18:31:02"></lastupdate></current>