<?xml version="1.0" encoding="UTF-8"?>
<current><city id="0" name="Weatogue"><coord lon="-72.8253" lat="41.8372"></coord><country>US</country><timezone>-14400</timezone><sun rise="2022-06-26T09:17:49" set="2022-06-27T00:30:19"></sun></city><temperature value="86.11" min="82.29" max="89.51" unit="fahrenheit"></temperature><feels_like value="91.67" unit="fahrenheit"></feels_like><humidity value="61" unit="%"></humidity><pressure value="1013" unit="hPa"></pressure><wind><speed value="4.61" unit="mph" name="Light breeze"></speed><gusts></gusts><direction value="160" code="SSE" name="South-southeast"></direction></wind><clouds value="20" name="few clouds"></clouds><visibility value="10000"></visibility><precipitation mode="no"></precipitation><weather number="801" value="few clouds" icon="02d"></weather><lastupdate value="2022-06-26T15:21:06"></lastupdate></current>