<?xml version="1.0" encoding="UTF-8"?>
<current><city id="0" name="Weatogue"><coord lon="-72.8253" lat="41.8372"></coord><country>US</country><timezone>-14400</timezone><sun rise="2022-03-31T10:35:41" set="2022-03-31T23:14:54"></sun></city><temperature value="38.79" min="35.94" max="44.78" unit="fahrenheit"></temperature><feels_like value="35.37" unit="fahrenheit"></feels_like><humidity value="91" unit="%"></humidity><pressure value="1007" unit="hPa"></pressure><wind><speed value="4.61" unit="mph" name="Light breeze"></speed><gusts></gusts><direction value="360" code="N" name="North"></direction></wind><clouds value="100" name="overcast clouds"></clouds><visibility value="4023"></visibility><precipitation mode="no"></precipitation><weather number="300" value="light intensity drizzle" icon="09d"></weather><lastupdate value="2022-03-31T11:29:06"></lastupdate></current>