<?xml version="1.0" encoding="UTF-8"?>
<current><city id="0" name="Weatogue"><coord lon="-72.8253" lat="41.8372"></coord><country>US</country><timezone>-18000</timezone><sun rise="2022-02-27T11:29:37" set="2022-02-27T22:38:46"></sun></city><temperature value="25.25" min="25.25" max="25.25" unit="fahrenheit"></temperature><feels_like value="16.27" unit="fahrenheit"></feels_like><humidity value="79" unit="%"></humidity><pressure value="1018" unit="hPa"></pressure><wind><speed value="8.52" unit="mph" name="Gentle Breeze"></speed><gusts value="24.43"></gusts><direction value="245" code="WSW" name="West-southwest"></direction></wind><clouds value="7" name="clear sky"></clouds><visibility value="10000"></visibility><precipitation mode="no"></precipitation><weather number="800" value="clear sky" icon="01d"></weather><lastupdate value="2022-02-27T13:02:53"></lastupdate></current>