<?xml version="1.0" encoding="UTF-8"?>
<current><city id="0" name="Weatogue"><coord lon="-72.8253" lat="41.8372"></coord><country>US</country><timezone>-14400</timezone><sun rise="2022-06-30T09:19:28" set="2022-07-01T00:30:11"></sun></city><temperature value="70.68" min="67.41" max="74.8" unit="fahrenheit"></temperature><feels_like value="70.93" unit="fahrenheit"></feels_like><humidity value="74" unit="%"></humidity><pressure value="1010" unit="hPa"></pressure><wind><speed value="4.59" unit="mph" name="Light breeze"></speed><gusts value="10.94"></gusts><direction value="195" code="SSW" name="South-southwest"></direction></wind><clouds value="27" name="scattered clouds"></clouds><visibility value="10000"></visibility><precipitation mode="no"></precipitation><weather number="802" value="scattered clouds" icon="03n"></weather><lastupdate value="2022-07-01T01:27:48"></lastupdate></current>