<?xml version="1.0" encoding="UTF-8"?>
<current><city id="0" name="West New York"><coord lon="-74.0115" lat="40.7888"></coord><country>US</country><timezone>-18000</timezone><sun rise="2021-11-29T11:59:20" set="2021-11-29T21:30:00"></sun></city><temperature value="36.05" min="32.07" max="38.68" unit="fahrenheit"></temperature><feels_like value="30.97" unit="fahrenheit"></feels_like><humidity value="66" unit="%"></humidity><pressure value="1010" unit="hPa"></pressure><wind><speed value="6.11" unit="mph" name="Light breeze"></speed><gusts value="12.12"></gusts><direction value="287" code="WNW" name="West-northwest"></direction></wind><clouds value="100" name="overcast clouds"></clouds><visibility value="10000"></visibility><precipitation mode="no"></precipitation><weather number="804" value="overcast clouds" icon="04n"></weather><lastupdate value="2021-11-29T07:55:42"></lastupdate></current>