<?xml version="1.0" encoding="UTF-8"?>
<current><city id="0" name="Dunedin"><coord lon="-82.7794" lat="28.0284"></coord><country>US</country><timezone>-14400</timezone><sun rise="2022-05-28T10:36:03" set="2022-05-29T00:21:07"></sun></city><temperature value="77.77" min="75.18" max="79.09" unit="fahrenheit"></temperature><feels_like value="79.11" unit="fahrenheit"></feels_like><humidity value="82" unit="%"></humidity><pressure value="1013" unit="hPa"></pressure><wind><speed value="4" unit="mph" name="Light breeze"></speed><gusts value="7"></gusts><direction value="229" code="SW" name="Southwest"></direction></wind><clouds value="75" name="broken clouds"></clouds><visibility value="10000"></visibility><precipitation mode="no"></precipitation><weather number="803" value="broken clouds" icon="04n"></weather><lastupdate value="2022-05-28T04:56:03"></lastupdate></current>