<?xml version="1.0" encoding="UTF-8"?>
<current><city id="0" name="Weatogue"><coord lon="-72.8253" lat="41.8372"></coord><country>US</country><timezone>-14400</timezone><sun rise="2022-04-15T10:10:51" set="2022-04-15T23:31:21"></sun></city><temperature value="53.87" min="50.83" max="56.48" unit="fahrenheit"></temperature><feels_like value="51.31" unit="fahrenheit"></feels_like><humidity value="50" unit="%"></humidity><pressure value="1015" unit="hPa"></pressure><wind><speed value="17.27" unit="mph" name="Moderate breeze"></speed><gusts></gusts><direction value="170" code="S" name="South"></direction></wind><clouds value="20" name="few clouds"></clouds><visibility value="10000"></visibility><precipitation mode="no"></precipitation><weather number="801" value="few clouds" icon="02n"></weather><lastupdate value="2022-04-16T03:35:55"></lastupdate></current>