<?xml version="1.0" encoding="UTF-8"?>
<current><city id="0" name="Weatogue"><coord lon="-72.8253" lat="41.8372"></coord><country>US</country><timezone>-18000</timezone><sun rise="2022-03-09T11:13:24" set="2022-03-09T22:50:29"></sun></city><temperature value="30.31" min="27.48" max="33.96" unit="fahrenheit"></temperature><feels_like value="30.31" unit="fahrenheit"></feels_like><humidity value="78" unit="%"></humidity><pressure value="1002" unit="hPa"></pressure><wind><speed value="2.19" unit="mph" name="Calm"></speed><gusts value="5.21"></gusts><direction value="137" code="SE" name="SouthEast"></direction></wind><clouds value="100" name="overcast clouds"></clouds><visibility value="4143"></visibility><precipitation mode="no"></precipitation><weather number="804" value="overcast clouds" icon="04n"></weather><lastupdate value="2022-03-09T10:58:56"></lastupdate></current>