<?xml version="1.0" encoding="UTF-8"?>
<current><city id="0" name="Weatogue"><coord lon="-72.8253" lat="41.8372"></coord><country>US</country><timezone>-18000</timezone><sun rise="2022-03-06T11:18:23" set="2022-03-06T22:47:02"></sun></city><temperature value="60.84" min="52.56" max="64.65" unit="fahrenheit"></temperature><feels_like value="60.28" unit="fahrenheit"></feels_like><humidity value="78" unit="%"></humidity><pressure value="1012" unit="hPa"></pressure><wind><speed value="13.8" unit="mph" name="Moderate breeze"></speed><gusts value="17.27"></gusts><direction value="200" code="SSW" name="South-southwest"></direction></wind><clouds value="0" name="clear sky"></clouds><visibility value="10000"></visibility><precipitation mode="no"></precipitation><weather number="800" value="clear sky" icon="01d"></weather><lastupdate value="2022-03-06T20:51:10"></lastupdate></current>