<?xml version="1.0" encoding="UTF-8"?>
<current><city id="0" name="Weatogue"><coord lon="-72.8253" lat="41.8372"></coord><country>US</country><timezone>-18000</timezone><sun rise="2022-01-24T12:10:50" set="2022-01-24T21:55:40"></sun></city><temperature value="28.06" min="24.84" max="31.75" unit="fahrenheit"></temperature><feels_like value="21.76" unit="fahrenheit"></feels_like><humidity value="79" unit="%"></humidity><pressure value="1009" unit="hPa"></pressure><wind><speed value="5.75" unit="mph" name="Light breeze"></speed><gusts></gusts><direction value="200" code="SSW" name="South-southwest"></direction></wind><clouds value="100" name="overcast clouds"></clouds><visibility value="9656"></visibility><precipitation mode="no"></precipitation><weather number="600" value="light snow" icon="13n"></weather><lastupdate value="2022-01-25T03:11:40"></lastupdate></current>