<?xml version="1.0" encoding="UTF-8"?>
<current><city id="0" name="Weatogue"><coord lon="-72.8253" lat="41.8372"></coord><country>US</country><timezone>-14400</timezone><sun rise="2022-05-25T09:23:00" set="2022-05-26T00:13:49"></sun></city><temperature value="73.45" min="68.94" max="76.14" unit="fahrenheit"></temperature><feels_like value="72.75" unit="fahrenheit"></feels_like><humidity value="48" unit="%"></humidity><pressure value="1019" unit="hPa"></pressure><wind><speed value="11.5" unit="mph" name="Gentle Breeze"></speed><gusts value="20.71"></gusts><direction value="180" code="S" name="South"></direction></wind><clouds value="75" name="broken clouds"></clouds><visibility value="10000"></visibility><precipitation mode="no"></precipitation><weather number="803" value="broken clouds" icon="04d"></weather><lastupdate value="2022-05-25T20:06:10"></lastupdate></current>