<?xml version="1.0" encoding="UTF-8"?>
<current><city id="0" name="West New York"><coord lon="-74.0115" lat="40.7888"></coord><country>US</country><timezone>-14400</timezone><sun rise="2022-05-07T09:47:11" set="2022-05-07T23:57:58"></sun></city><temperature value="46.76" min="44.42" max="49.44" unit="fahrenheit"></temperature><feels_like value="37.94" unit="fahrenheit"></feels_like><humidity value="91" unit="%"></humidity><pressure value="1011" unit="hPa"></pressure><wind><speed value="28.01" unit="mph" name="Strong breeze"></speed><gusts value="38.99"></gusts><direction value="53" code="NE" name="NorthEast"></direction></wind><clouds value="100" name="overcast clouds"></clouds><visibility value="4828"></visibility><precipitation value="1.5" mode="rain" unit="1h"></precipitation><weather number="501" value="moderate rain" icon="10d"></weather><lastupdate value="2022-05-07T18:50:37"></lastupdate></current>