<?xml version="1.0" encoding="UTF-8"?>
<current><city id="0" name="Weatogue"><coord lon="-72.8253" lat="41.8372"></coord><country>US</country><timezone>-18000</timezone><sun rise="2021-11-16T11:42:27" set="2021-11-16T21:30:04"></sun></city><temperature value="43.18" min="40.26" max="45.97" unit="fahrenheit"></temperature><feels_like value="40.98" unit="fahrenheit"></feels_like><humidity value="59" unit="%"></humidity><pressure value="1013" unit="hPa"></pressure><wind><speed value="4" unit="mph" name="Light breeze"></speed><gusts value="8.01"></gusts><direction value="269" code="W" name="West"></direction></wind><clouds value="20" name="few clouds"></clouds><visibility value="10000"></visibility><precipitation mode="no"></precipitation><weather number="801" value="few clouds" icon="02d"></weather><lastupdate value="2021-11-16T15:28:11"></lastupdate></current>