<?xml version="1.0" encoding="UTF-8"?>
<current><city id="0" name="Dunedin"><coord lon="-82.7794" lat="28.0284"></coord><country>US</country><timezone>-14400</timezone><sun rise="2022-05-02T10:50:16" set="2022-05-03T00:05:46"></sun></city><temperature value="83.95" min="79.95" max="90.05" unit="fahrenheit"></temperature><feels_like value="89.13" unit="fahrenheit"></feels_like><humidity value="66" unit="%"></humidity><pressure value="1016" unit="hPa"></pressure><wind><speed value="7" unit="mph" name="Light breeze"></speed><gusts value="14"></gusts><direction value="214" code="SW" name="Southwest"></direction></wind><clouds value="40" name="scattered clouds"></clouds><visibility value="10000"></visibility><precipitation mode="no"></precipitation><weather number="802" value="scattered clouds" icon="03d"></weather><lastupdate value="2022-05-02T19:55:43"></lastupdate></current>