<?xml version="1.0" encoding="UTF-8"?>
<current><city id="0" name="Weatogue"><coord lon="-72.8253" lat="41.8372"></coord><country>US</country><timezone>-14400</timezone><sun rise="2022-07-13T09:27:43" set="2022-07-14T00:25:57"></sun></city><temperature value="81.77" min="76.14" max="87.26" unit="fahrenheit"></temperature><feels_like value="83.77" unit="fahrenheit"></feels_like><humidity value="58" unit="%"></humidity><pressure value="1008" unit="hPa"></pressure><wind><speed value="6.91" unit="mph" name="Light breeze"></speed><gusts></gusts><direction value="30" code="NNE" name="North-northeast"></direction></wind><clouds value="20" name="few clouds"></clouds><visibility value="10000"></visibility><precipitation mode="no"></precipitation><weather number="801" value="few clouds" icon="02d"></weather><lastupdate value="2022-07-13T23:30:57"></lastupdate></current>