<?xml version="1.0" encoding="UTF-8"?>
<current><city id="0" name="Dunedin"><coord lon="-82.7794" lat="28.0284"></coord><country>US</country><timezone>-14400</timezone><sun rise="2022-05-04T10:48:42" set="2022-05-05T00:06:58"></sun></city><temperature value="82.35" min="77" max="89.06" unit="fahrenheit"></temperature><feels_like value="88.07" unit="fahrenheit"></feels_like><humidity value="74" unit="%"></humidity><pressure value="1017" unit="hPa"></pressure><wind><speed value="10.36" unit="mph" name="Gentle Breeze"></speed><gusts></gusts><direction value="260" code="W" name="West"></direction></wind><clouds value="75" name="broken clouds"></clouds><visibility value="10000"></visibility><precipitation mode="no"></precipitation><weather number="803" value="broken clouds" icon="04d"></weather><lastupdate value="2022-05-04T17:50:47"></lastupdate></current>