<?xml version="1.0" encoding="UTF-8"?>
<current><city id="0" name="West New York"><coord lon="-74.0115" lat="40.7888"></coord><country>US</country><timezone>-14400</timezone><sun rise="2022-04-17T10:13:56" set="2022-04-17T23:36:50"></sun></city><temperature value="43.38" min="40.44" max="46.51" unit="fahrenheit"></temperature><feels_like value="34.75" unit="fahrenheit"></feels_like><humidity value="51" unit="%"></humidity><pressure value="1020" unit="hPa"></pressure><wind><speed value="20.71" unit="mph" name="Fresh Breeze"></speed><gusts></gusts><direction value="310" code="NW" name="Northwest"></direction></wind><clouds value="0" name="clear sky"></clouds><visibility value="10000"></visibility><precipitation mode="no"></precipitation><weather number="800" value="clear sky" icon="01d"></weather><lastupdate value="2022-04-17T13:04:00"></lastupdate></current>