<?xml version="1.0" encoding="UTF-8"?>
<current><city id="0" name="Weatogue"><coord lon="-72.8253" lat="41.8372"></coord><country>US</country><timezone>-14400</timezone><sun rise="2021-07-07T09:23:35" set="2021-07-08T00:28:32"></sun></city><temperature value="88.16" min="80.85" max="93.06" unit="fahrenheit"></temperature><feels_like value="93.29" unit="fahrenheit"></feels_like><humidity value="55" unit="%"></humidity><pressure value="1011" unit="hPa"></pressure><wind><speed value="10" unit="mph" name="Gentle Breeze"></speed><gusts value="31"></gusts><direction value="98" code="E" name="East"></direction></wind><clouds value="75" name="broken clouds"></clouds><visibility value="10000"></visibility><precipitation mode="no"></precipitation><weather number="211" value="thunderstorm" icon="11d"></weather><lastupdate value="2021-07-07T21:16:32"></lastupdate></current>